geoapi_client/__init__.py
geoapi_client/api_client.py
geoapi_client/configuration.py
geoapi_client/rest.py
geoapi_client/api/__init__.py
geoapi_client/api/notifications_api.py
geoapi_client/api/projects_api.py
geoapi_client/api/public_projects_api.py
geoapi_client/api/streetview_api.py
geoapi_client/models/__init__.py
geoapi_client/models/asset.py
geoapi_client/models/feature.py
geoapi_client/models/feature_collection.py
geoapi_client/models/notification_response.py
geoapi_client/models/ok_response.py
geoapi_client/models/overlay.py
geoapi_client/models/payload.py
geoapi_client/models/point_cloud.py
geoapi_client/models/progress_notification_response.py
geoapi_client/models/project.py
geoapi_client/models/streetview.py
geoapi_client/models/streetview_instance.py
geoapi_client/models/streetview_organization.py
geoapi_client/models/streetview_params.py
geoapi_client/models/streetview_sequence.py
geoapi_client/models/tapis_file.py
geoapi_client/models/tapis_file_import.py
geoapi_client/models/tapis_file_upload.py
geoapi_client/models/tapis_folder_import.py
geoapi_client/models/task.py
geoapi_client/models/tile_server.py
geoapi_client/models/user.py
geoapi_client/models/user_payload.py
test/__init__.py
test/test_asset.py
test/test_feature.py
test/test_feature_collection.py
test/test_notification_response.py
test/test_notifications_api.py
test/test_ok_response.py
test/test_overlay.py
test/test_payload.py
test/test_point_cloud.py
test/test_progress_notification_response.py
test/test_project.py
test/test_projects_api.py
test/test_public_projects_api.py
test/test_streetview.py
test/test_streetview_api.py
test/test_streetview_instance.py
test/test_streetview_organization.py
test/test_streetview_params.py
test/test_streetview_sequence.py
test/test_tapis_file.py
test/test_tapis_file_import.py
test/test_tapis_file_upload.py
test/test_tapis_folder_import.py
test/test_task.py
test/test_tile_server.py
test/test_user.py
test/test_user_payload.py
geoapi_client-2.10.dist-info/METADATA
geoapi_client-2.10.dist-info/WHEEL
geoapi_client-2.10.dist-info/top_level.txt
geoapi_client-2.10.dist-info/RECORD
