Metadata-Version: 2.1
Name: geoapi-client
Version: 2.10
Summary: GeoAPI: Geospatial API for TAPIS 
Home-page: https://github.com/TACC-Cloud/geoapi
Author: Texas Advanced Computing Center
Author-email: CICsupport@tacc.utexas.edu
License: UNKNOWN
Keywords: TACC,GeoAPI
Platform: UNKNOWN
Requires-Dist: certifi (>=2017.4.17)
Requires-Dist: python-dateutil (>=2.1)
Requires-Dist: six (>=1.10)
Requires-Dist: urllib3 (>=1.23)
